[
  {
    "name": "announcement",
    "params": {
      "title": "Consejería de Familia, Juventud y Asuntos Sociales",
      "description": "Adenda de 29 de noviembre de 2024, de prórroga para el año 2025 del convenio de colaboración entre la Comunidad de Madrid y el Ayuntamiento de Mejorada del Campo para la realización de actuaciones contra la violencia de género y para la promoción de la igualdad de oportunidades entre mujeres y hombres",
      "file": "https://www.bocm.es/boletin/CM_Orden_BOCM/2024/12/21/BOCM-20241221-13.PDF"
    }
  }
]